zeebgram/__init__.py
zeebgram/client.py
zeebgram/dispatcher.py
zeebgram/emoji.py
zeebgram/file_id.py
zeebgram/filters.py
zeebgram/mime_types.py
zeebgram/py.typed
zeebgram/sync.py
zeebgram/utils.py
zeebgram/connection/__init__.py
zeebgram/connection/connection.py
zeebgram/connection/transport/__init__.py
zeebgram/connection/transport/tcp/__init__.py
zeebgram/connection/transport/tcp/tcp.py
zeebgram/connection/transport/tcp/tcp_abridged.py
zeebgram/connection/transport/tcp/tcp_abridged_o.py
zeebgram/connection/transport/tcp/tcp_full.py
zeebgram/connection/transport/tcp/tcp_intermediate.py
zeebgram/connection/transport/tcp/tcp_intermediate_o.py
zeebgram/crypto/__init__.py
zeebgram/crypto/aes.py
zeebgram/crypto/mtproto.py
zeebgram/crypto/prime.py
zeebgram/crypto/rsa.py
zeebgram/enums/__init__.py
zeebgram/enums/auto_name.py
zeebgram/enums/chat_action.py
zeebgram/enums/chat_event_action.py
zeebgram/enums/chat_member_status.py
zeebgram/enums/chat_members_filter.py
zeebgram/enums/chat_type.py
zeebgram/enums/message_entity_type.py
zeebgram/enums/message_media_type.py
zeebgram/enums/message_service_type.py
zeebgram/enums/messages_filter.py
zeebgram/enums/next_code_type.py
zeebgram/enums/parse_mode.py
zeebgram/enums/poll_type.py
zeebgram/enums/sent_code_type.py
zeebgram/enums/stories_privacy_rules.py
zeebgram/enums/user_status.py
zeebgram/errors/__init__.py
zeebgram/errors/rpc_error.py
zeebgram/handlers/__init__.py
zeebgram/handlers/callback_query_handler.py
zeebgram/handlers/chat_join_request_handler.py
zeebgram/handlers/chat_member_updated_handler.py
zeebgram/handlers/chosen_inline_result_handler.py
zeebgram/handlers/deleted_messages_handler.py
zeebgram/handlers/disconnect_handler.py
zeebgram/handlers/edited_message_handler.py
zeebgram/handlers/handler.py
zeebgram/handlers/inline_query_handler.py
zeebgram/handlers/message_handler.py
zeebgram/handlers/poll_handler.py
zeebgram/handlers/raw_update_handler.py
zeebgram/handlers/story_handler.py
zeebgram-0.1.5.dist-info/licenses/COPYING
zeebgram-0.1.5.dist-info/licenses/COPYING.lesser
zeebgram-0.1.5.dist-info/licenses/LICENSE
zeebgram-0.1.5.dist-info/licenses/NOTICE
zeebgram-0.1.5.dist-info/METADATA
zeebgram-0.1.5.dist-info/WHEEL
zeebgram-0.1.5.dist-info/top_level.txt
zeebgram-0.1.5.dist-info/RECORD
