Metadata-Version: 2.4
Name: zeebgram
Version: 0.1.5
Summary: Custom Pyrogram for your userbot
Author: ZeebFly
License: MIT
Requires-Python: >=3.7
License-File: LICENSE
License-File: COPYING
License-File: COPYING.lesser
License-File: NOTICE
Requires-Dist: tgcrypto
Requires-Dist: pysocks
Dynamic: license-file
